liteai/__init__.py
liteai/api.py
liteai/cli.py
liteai/config.py
liteai/core.py
liteai/modelcard.py
liteai/tool.py
liteai/utils.py
liteai/voice.py
liteai/provider/__init__.py
liteai/provider/api.py
liteai/provider/base.py
liteai/provider/coze.py
liteai/provider/deepseek.py
liteai/provider/doubao.py
liteai/provider/lite_llm.py
liteai/provider/minimax.py
liteai/provider/open_ai.py
liteai/provider/qwen.py
liteai/provider/siliconflow.py
liteai/provider/tgi.py
liteai/provider/xunfei.py
liteai/provider/zhipu.py
liteai-0.2.2.dist-info/METADATA
liteai-0.2.2.dist-info/WHEEL
liteai-0.2.2.dist-info/licenses/LICENSE
liteai-0.2.2.dist-info/RECORD
