Metadata-Version: 2.4
Name: liteai
Version: 0.2.2
Summary: lite ai client
Author-email: jerry <jerrychen1990@gmail.com>
License-File: LICENSE
Classifier: License :: OSI Approved :: MIT License
Classifier: Programming Language :: Python :: 3
Requires-Python: >=3.10
Requires-Dist: cozepy>=0.13.1
Requires-Dist: dashscope>=1.20.0
Requires-Dist: litellm>=1.49.1
Requires-Dist: openai>=1.4.1
Requires-Dist: pillow>=10.3.0
Requires-Dist: pydub>=0.25.1
Requires-Dist: python-dotenv>=1.0.1
Requires-Dist: python-snippets>=0.1.3
Requires-Dist: volcengine-python-sdk[ark]>=1.0.94
Requires-Dist: zhipuai>=2.1.4.20230812
